coverage2sketch.py
coverage2sketch-0.1.0.dist-info/licenses/LICENSE
coverage2sketch-0.1.0.dist-info/METADATA
coverage2sketch-0.1.0.dist-info/WHEEL
coverage2sketch-0.1.0.dist-info/top_level.txt
coverage2sketch-0.1.0.dist-info/RECORD
