Metadata-Version: 2.4
Name: coverage2sketch
Version: 0.1.0
Summary: A tool to extract "sketches" of Python source files based on coverage data.
Author-email: Jifeng Wu <jifengwu2k@gmail.com>
License-Expression: MIT
Project-URL: Homepage, https://github.com/jifengwu2k/coverage2sketch
Project-URL: Bug Tracker, https://github.com/jifengwu2k/coverage2sketch/issues
Classifier: Programming Language :: Python :: 3
Classifier: Operating System :: OS Independent
Requires-Python: >=3
License-File: LICENSE
Requires-Dist: astor
Requires-Dist: coverage
Dynamic: license-file
